nota/__init__.py
nota/main.py
nota/templates/bug.md
nota/templates/defect.md
nota/templates/feature.md
nota/templates/story.md
rats3g_nota-0.1.3.dist-info/LICENSE
rats3g_nota-0.1.3.dist-info/METADATA
rats3g_nota-0.1.3.dist-info/WHEEL
rats3g_nota-0.1.3.dist-info/entry_points.txt
rats3g_nota-0.1.3.dist-info/top_level.txt
rats3g_nota-0.1.3.dist-info/RECORD
