Metadata-Version: 2.1
Name: rats3g-nota
Version: 0.1.3
Summary: A scaffolding program for developer notes.
Home-page: https://github.com/rats3g/nota
Author: Robert Taylor
Author-email: rats3g@gmail.com
License: mit
Project-URL: Source, https://github.com/rats3g/nota
Platform: any
Classifier: Development Status :: 3 - Alpha
Classifier: Programming Language :: Python
Classifier: Environment :: Console
Classifier: Intended Audience :: Developers
Classifier: License :: OSI Approved :: MIT License
Requires-Dist: appdirs
Requires-Dist: pyscaffold
